<annotation>
  <folder></folder>
  <filename>119.jpg</filename>
  <source>
    <database>Unknown</database>
    <annotation>Unknown</annotation>
    <image>Unknown</image>
  </source>
  <size>
    <width>1920</width>
    <height>1080</height>
    <depth>3</depth>
  </size>
  <segmented>0</segmented>
  <object>
    <name>person</name>
    <occluded>0</occluded>
    <bndbox>
      <xmin>1057.529296875</xmin>
      <ymin>423.7396484375</ymin>
      <xmax>1128.899999542239</xmax>
      <ymax>595.2400000000009</ymax>
    </bndbox>
  </object>
  <object>
    <name>person</name>
    <occluded>0</occluded>
    <bndbox>
      <xmin>1172.662109375</xmin>
      <ymin>215.7099609375</ymin>
      <xmax>1214.7000000000007</xmax>
      <ymax>334.2100000000002</ymax>
    </bndbox>
  </object>
  <object>
    <name>person</name>
    <occluded>0</occluded>
    <bndbox>
      <xmin>684.3310546875</xmin>
      <ymin>222.0396484375</ymin>
      <xmax>739.6299998474148</xmax>
      <ymax>375.1400000000009</ymax>
    </bndbox>
  </object>
  <object>
    <name>person</name>
    <occluded>0</occluded>
    <bndbox>
      <xmin>715.88671875</xmin>
      <ymin>143.4458984375</ymin>
      <xmax>763.189453125</xmax>
      <ymax>274.7700000000015</ymax>
    </bndbox>
  </object>
  <object>
    <name>person</name>
    <occluded>0</occluded>
    <bndbox>
      <xmin>1745.8752148437507</xmin>
      <ymin>880.52236328125</ymin>
      <xmax>1852.5117773437516</xmax>
      <ymax>1044.3050000000012</ymax>
    </bndbox>
  </object>
  <object>
    <name>person</name>
    <occluded>0</occluded>
    <bndbox>
      <xmin>1770.108984375</xmin>
      <ymin>311.35988281250064</ymin>
      <xmax>1845.1389439392065</xmax>
      <ymax>475.82988922119114</ymax>
    </bndbox>
  </object>
  <object>
    <name>person</name>
    <occluded>0</occluded>
    <bndbox>
      <xmin>1715.9</xmin>
      <ymin>153.58000000000283</ymin>
      <xmax>1781.1381777191182</xmax>
      <ymax>292.0400054931641</ymax>
    </bndbox>
  </object>
  <object>
    <name>person</name>
    <occluded>0</occluded>
    <bndbox>
      <xmin>1747.9100000000012</xmin>
      <ymin>80.510546875</ymin>
      <xmax>1788.249997329712</xmax>
      <ymax>165.29914230346404</ymax>
    </bndbox>
  </object>
  <object>
    <name>person</name>
    <occluded>0</occluded>
    <bndbox>
      <xmin>1380.45078125</xmin>
      <ymin>30.75</ymin>
      <xmax>1418.200703811643</xmax>
      <ymax>166.60000549316428</ymax>
    </bndbox>
  </object>
  <object>
    <name>person</name>
    <occluded>0</occluded>
    <bndbox>
      <xmin>906.400390625</xmin>
      <ymin>426.36000000000274</ymin>
      <xmax>975.0700000000008</xmax>
      <ymax>591.1000091552735</ymax>
    </bndbox>
  </object>
  <object>
    <name>person</name>
    <occluded>0</occluded>
    <bndbox>
      <xmin>1120.8400390625</xmin>
      <ymin>234.42000000000007</ymin>
      <xmax>1174.4099979400635</xmax>
      <ymax>353.4499938964844</ymax>
    </bndbox>
  </object>
  <object>
    <name>person</name>
    <occluded>0</occluded>
    <bndbox>
      <xmin>699.4416015625</xmin>
      <ymin>1.3199218750000004</ymin>
      <xmax>745.4412109375014</xmax>
      <ymax>117.96000000000022</ymax>
    </bndbox>
  </object>
  <object>
    <name>person</name>
    <occluded>0</occluded>
    <bndbox>
      <xmin>536.6849609375</xmin>
      <ymin>541.79375</ymin>
      <xmax>613.7510553741449</xmax>
      <ymax>698.5600027465822</ymax>
    </bndbox>
  </object>
  <object>
    <name>person</name>
    <occluded>0</occluded>
    <bndbox>
      <xmin>555.1607421875</xmin>
      <ymin>415.22003906250063</ymin>
      <xmax>616.3007024383521</xmax>
      <ymax>557.7600109863284</ymax>
    </bndbox>
  </object>
  <object>
    <name>person</name>
    <occluded>0</occluded>
    <bndbox>
      <xmin>799.328125</xmin>
      <ymin>40.5400390625</ymin>
      <xmax>834.9281257629373</xmax>
      <ymax>168.5</ymax>
    </bndbox>
  </object>
  <object>
    <name>person</name>
    <occluded>0</occluded>
    <bndbox>
      <xmin>856.4</xmin>
      <ymin>44.0482421875</ymin>
      <xmax>896.1399990081787</xmax>
      <ymax>174.79000000000195</ymax>
    </bndbox>
  </object>
  <object>
    <name>person</name>
    <occluded>0</occluded>
    <bndbox>
      <xmin>972.590625</xmin>
      <ymin>312.08003906250195</ymin>
      <xmax>1030.260000000001</xmax>
      <ymax>468.85003601074203</ymax>
    </bndbox>
  </object>
  <object>
    <name>person</name>
    <occluded>0</occluded>
    <bndbox>
      <xmin>77.1396484375</xmin>
      <ymin>108.83125</ymin>
      <xmax>132.09000007629658</xmax>
      <ymax>228.39000000000198</ymax>
    </bndbox>
  </object>
  <object>
    <name>person</name>
    <occluded>0</occluded>
    <bndbox>
      <xmin>66.92578125</xmin>
      <ymin>987.134765625</ymin>
      <xmax>181.24785385131872</xmax>
      <ymax>1080.0</ymax>
    </bndbox>
  </object>
  <object>
    <name>person</name>
    <occluded>0</occluded>
    <bndbox>
      <xmin>335.3400000000009</xmin>
      <ymin>474.900390625</ymin>
      <xmax>400.499649810791</xmax>
      <ymax>629.0687499999985</ymax>
    </bndbox>
  </object>
  <object>
    <name>person</name>
    <occluded>0</occluded>
    <bndbox>
      <xmin>382.34765625</xmin>
      <ymin>491.0800000000014</ymin>
      <xmax>458.3984359741189</xmax>
      <ymax>651.1010345458984</ymax>
    </bndbox>
  </object>
  <object>
    <name>person</name>
    <occluded>0</occluded>
    <bndbox>
      <xmin>410.51394531250264</xmin>
      <ymin>465.69921875</ymin>
      <xmax>459.5</xmax>
      <ymax>590.3000000000029</ymax>
    </bndbox>
  </object>
  <object>
    <name>person</name>
    <occluded>0</occluded>
    <bndbox>
      <xmin>448.0</xmin>
      <ymin>493.871484375</ymin>
      <xmax>502.0999984741211</xmax>
      <ymax>624.2700000000001</ymax>
    </bndbox>
  </object>
  <object>
    <name>person</name>
    <occluded>0</occluded>
    <bndbox>
      <xmin>1222.7500000000007</xmin>
      <ymin>24.1669921875</ymin>
      <xmax>1252.5396062850953</xmax>
      <ymax>96.03000000000065</ymax>
    </bndbox>
  </object>
  <object>
    <name>person</name>
    <occluded>0</occluded>
    <bndbox>
      <xmin>1703.3505859375</xmin>
      <ymin>85.2400000000016</ymin>
      <xmax>1745.6805854797335</xmax>
      <ymax>198.1700012207031</ymax>
    </bndbox>
  </object>
  <object>
    <name>person</name>
    <occluded>0</occluded>
    <bndbox>
      <xmin>1010.68828125</xmin>
      <ymin>615.1953125</ymin>
      <xmax>1065.0</xmax>
      <ymax>788.7511718750029</ymax>
    </bndbox>
  </object>
  <object>
    <name>person</name>
    <occluded>0</occluded>
    <bndbox>
      <xmin>1602.4800000000002</xmin>
      <ymin>298.336328125</ymin>
      <xmax>1670.4831298828126</xmax>
      <ymax>464.941796875</ymax>
    </bndbox>
  </object>
  <object>
    <name>person</name>
    <occluded>0</occluded>
    <bndbox>
      <xmin>693.1200000000023</xmin>
      <ymin>762.9205078125</ymin>
      <xmax>779.5999984741211</xmax>
      <ymax>973.960000000001</ymax>
    </bndbox>
  </object>
  <object>
    <name>person</name>
    <occluded>0</occluded>
    <bndbox>
      <xmin>1207.2801562500026</xmin>
      <ymin>683.750390625</ymin>
      <xmax>1291.180158843994</xmax>
      <ymax>883.3900000000027</ymax>
    </bndbox>
  </object>
  <object>
    <name>person</name>
    <occluded>0</occluded>
    <bndbox>
      <xmin>263.78828125</xmin>
      <ymin>37.6451171875</ymin>
      <xmax>315.460000000002</xmax>
      <ymax>141.1041015625</ymax>
    </bndbox>
  </object>
  <object>
    <name>person</name>
    <occluded>0</occluded>
    <bndbox>
      <xmin>1284.6005859375</xmin>
      <ymin>0.0</ymin>
      <xmax>1319.5700000000022</xmax>
      <ymax>101.86000000000203</ymax>
    </bndbox>
  </object>
  <object>
    <name>person</name>
    <occluded>0</occluded>
    <bndbox>
      <xmin>914.5600390625</xmin>
      <ymin>96.83800000000156</ymin>
      <xmax>962.5880368804902</xmax>
      <ymax>228.65717224121093</ymax>
    </bndbox>
  </object>
  <object>
    <name>person</name>
    <occluded>0</occluded>
    <bndbox>
      <xmin>65.1521484375</xmin>
      <ymin>631.71484375</ymin>
      <xmax>152.75000000000074</xmax>
      <ymax>816.6494921875022</ymax>
    </bndbox>
  </object>
</annotation>
