<annotation>
  <folder></folder>
  <filename>25.jpg</filename>
  <source>
    <database>Unknown</database>
    <annotation>Unknown</annotation>
    <image>Unknown</image>
  </source>
  <size>
    <width>1920</width>
    <height>1080</height>
    <depth>3</depth>
  </size>
  <segmented>0</segmented>
  <object>
    <name>person</name>
    <occluded>0</occluded>
    <bndbox>
      <xmin>1109.7000000000007</xmin>
      <ymin>796.0</ymin>
      <xmax>1201.2517623901367</xmax>
      <ymax>993.8999938964844</ymax>
    </bndbox>
  </object>
  <object>
    <name>person</name>
    <occluded>0</occluded>
    <bndbox>
      <xmin>1310.599609375</xmin>
      <ymin>707.9000000000015</ymin>
      <xmax>1416.9996017456033</xmax>
      <ymax>885.7009887695312</ymax>
    </bndbox>
  </object>
  <object>
    <name>person</name>
    <occluded>0</occluded>
    <bndbox>
      <xmin>1500.5</xmin>
      <ymin>554.4000000000015</ymin>
      <xmax>1583.2009811401367</xmax>
      <ymax>737.5</ymax>
    </bndbox>
  </object>
  <object>
    <name>person</name>
    <occluded>0</occluded>
    <bndbox>
      <xmin>1142.5</xmin>
      <ymin>429.92578125</ymin>
      <xmax>1211.3245124816895</xmax>
      <ymax>575.8000000000029</ymax>
    </bndbox>
  </object>
  <object>
    <name>person</name>
    <occluded>0</occluded>
    <bndbox>
      <xmin>673.0</xmin>
      <ymin>529.099609375</ymin>
      <xmax>744.9503860473633</xmax>
      <ymax>721.6000000000022</ymax>
    </bndbox>
  </object>
  <object>
    <name>person</name>
    <occluded>0</occluded>
    <bndbox>
      <xmin>75.59765625</xmin>
      <ymin>826.5</ymin>
      <xmax>187.0009765625</xmax>
      <ymax>1002.3000030517578</ymax>
    </bndbox>
  </object>
  <object>
    <name>person</name>
    <occluded>0</occluded>
    <bndbox>
      <xmin>755.4523437500011</xmin>
      <ymin>367.224609375</ymin>
      <xmax>813.3500011444103</xmax>
      <ymax>522.3503906249989</ymax>
    </bndbox>
  </object>
  <object>
    <name>person</name>
    <occluded>0</occluded>
    <bndbox>
      <xmin>1488.060546875</xmin>
      <ymin>396.0</ymin>
      <xmax>1562.8490234375022</xmax>
      <ymax>559.3999938964844</ymax>
    </bndbox>
  </object>
  <object>
    <name>person</name>
    <occluded>0</occluded>
    <bndbox>
      <xmin>1805.9501953125</xmin>
      <ymin>187.0244140625</ymin>
      <xmax>1866.5543952941898</xmax>
      <ymax>319.1754882812511</ymax>
    </bndbox>
  </object>
  <object>
    <name>person</name>
    <occluded>0</occluded>
    <bndbox>
      <xmin>1717.150390625</xmin>
      <ymin>195.796875</ymin>
      <xmax>1779.3377872467026</xmax>
      <ymax>340.15000000000146</ymax>
    </bndbox>
  </object>
  <object>
    <name>person</name>
    <occluded>0</occluded>
    <bndbox>
      <xmin>1737.5052734375004</xmin>
      <ymin>111.3486328125</ymin>
      <xmax>1796.4299816131606</xmax>
      <ymax>215.7735183715813</ymax>
    </bndbox>
  </object>
  <object>
    <name>person</name>
    <occluded>0</occluded>
    <bndbox>
      <xmin>1680.800000000001</xmin>
      <ymin>32.177734375</ymin>
      <xmax>1735.3488960266113</xmax>
      <ymax>161.71179046631005</ymax>
    </bndbox>
  </object>
  <object>
    <name>person</name>
    <occluded>0</occluded>
    <bndbox>
      <xmin>1626.02734375</xmin>
      <ymin>19.6103515625</ymin>
      <xmax>1665.7013813018784</xmax>
      <ymax>133.10000000000218</ymax>
    </bndbox>
  </object>
  <object>
    <name>person</name>
    <occluded>0</occluded>
    <bndbox>
      <xmin>1382.4996093750015</xmin>
      <ymin>46.081445312500364</ymin>
      <xmax>1420.1091369628903</xmax>
      <ymax>177.3504867553711</ymax>
    </bndbox>
  </object>
  <object>
    <name>person</name>
    <occluded>0</occluded>
    <bndbox>
      <xmin>1199.869140625</xmin>
      <ymin>81.70000000000073</ymin>
      <xmax>1245.050000000003</xmax>
      <ymax>218.10000610351562</ymax>
    </bndbox>
  </object>
  <object>
    <name>person</name>
    <occluded>0</occluded>
    <bndbox>
      <xmin>1167.517578125</xmin>
      <ymin>100.69921875</ymin>
      <xmax>1216.4269523620605</xmax>
      <ymax>227.0</ymax>
    </bndbox>
  </object>
  <object>
    <name>person</name>
    <occluded>0</occluded>
    <bndbox>
      <xmin>927.0</xmin>
      <ymin>211.30078125</ymin>
      <xmax>985.1000000000022</xmax>
      <ymax>346.40000000000146</ymax>
    </bndbox>
  </object>
  <object>
    <name>person</name>
    <occluded>0</occluded>
    <bndbox>
      <xmin>1092.685546875</xmin>
      <ymin>75.015625</ymin>
      <xmax>1137.0503913879365</xmax>
      <ymax>184.40000000000146</ymax>
    </bndbox>
  </object>
  <object>
    <name>person</name>
    <occluded>0</occluded>
    <bndbox>
      <xmin>698.6015625</xmin>
      <ymin>174.5</ymin>
      <xmax>755.0</xmax>
      <ymax>311.7000000000007</ymax>
    </bndbox>
  </object>
  <object>
    <name>person</name>
    <occluded>0</occluded>
    <bndbox>
      <xmin>569.9775390625</xmin>
      <ymin>314.4365234375</ymin>
      <xmax>635.6001945495609</xmax>
      <ymax>451.9643737792976</ymax>
    </bndbox>
  </object>
  <object>
    <name>person</name>
    <occluded>0</occluded>
    <bndbox>
      <xmin>573.96875</xmin>
      <ymin>234.28125</ymin>
      <xmax>623.5622922897346</xmax>
      <ymax>329.1720703124993</ymax>
    </bndbox>
  </object>
  <object>
    <name>person</name>
    <occluded>0</occluded>
    <bndbox>
      <xmin>798.072265625</xmin>
      <ymin>55.5</ymin>
      <xmax>831.4000000000015</xmax>
      <ymax>189.12411499023438</ymax>
    </bndbox>
  </object>
  <object>
    <name>person</name>
    <occluded>0</occluded>
    <bndbox>
      <xmin>845.9296875</xmin>
      <ymin>56.5</ymin>
      <xmax>887.6000000000022</xmax>
      <ymax>187.67567443847656</ymax>
    </bndbox>
  </object>
  <object>
    <name>person</name>
    <occluded>0</occluded>
    <bndbox>
      <xmin>995.025390625</xmin>
      <ymin>135.81640625</ymin>
      <xmax>1046.1507808685274</xmax>
      <ymax>275.0</ymax>
    </bndbox>
  </object>
  <object>
    <name>person</name>
    <occluded>0</occluded>
    <bndbox>
      <xmin>917.4000000000015</xmin>
      <ymin>56.00390625</ymin>
      <xmax>953.0</xmax>
      <ymax>170.60000000000218</ymax>
    </bndbox>
  </object>
  <object>
    <name>person</name>
    <occluded>0</occluded>
    <bndbox>
      <xmin>395.615234375</xmin>
      <ymin>0.0</ymin>
      <xmax>436.025390625</xmax>
      <ymax>96.24560546875</ymax>
    </bndbox>
  </object>
  <object>
    <name>person</name>
    <occluded>0</occluded>
    <bndbox>
      <xmin>273.0</xmin>
      <ymin>3.43359375</ymin>
      <xmax>336.0</xmax>
      <ymax>117.60000000000218</ymax>
    </bndbox>
  </object>
  <object>
    <name>person</name>
    <occluded>0</occluded>
    <bndbox>
      <xmin>88.6220703125</xmin>
      <ymin>123.9873046875</ymin>
      <xmax>137.2511248588562</xmax>
      <ymax>242.7760238647461</ymax>
    </bndbox>
  </object>
  <object>
    <name>person</name>
    <occluded>0</occluded>
    <bndbox>
      <xmin>232.400390625</xmin>
      <ymin>518.5</ymin>
      <xmax>304.20039520263526</xmax>
      <ymax>701.1000061035156</ymax>
    </bndbox>
  </object>
  <object>
    <name>person</name>
    <occluded>0</occluded>
    <bndbox>
      <xmin>337.82421875</xmin>
      <ymin>485.6943359375</ymin>
      <xmax>400.70000000000255</xmax>
      <ymax>634.7000000000007</ymax>
    </bndbox>
  </object>
  <object>
    <name>person</name>
    <occluded>0</occluded>
    <bndbox>
      <xmin>378.353515625</xmin>
      <ymin>503.5576171875</ymin>
      <xmax>448.8058593750029</xmax>
      <ymax>663.3564727783214</ymax>
    </bndbox>
  </object>
  <object>
    <name>person</name>
    <occluded>0</occluded>
    <bndbox>
      <xmin>419.966796875</xmin>
      <ymin>480.4501953125</ymin>
      <xmax>461.8000000000029</xmax>
      <ymax>600.8499984741211</ymax>
    </bndbox>
  </object>
  <object>
    <name>person</name>
    <occluded>0</occluded>
    <bndbox>
      <xmin>454.4150390625</xmin>
      <ymin>505.2255859375</ymin>
      <xmax>508.1696296691898</xmax>
      <ymax>637.720703125</ymax>
    </bndbox>
  </object>
  <object>
    <name>person</name>
    <occluded>0</occluded>
    <bndbox>
      <xmin>1298.2000000000007</xmin>
      <ymin>0.0</ymin>
      <xmax>1336.2078247070312</xmax>
      <ymax>100.51337890625291</ymax>
    </bndbox>
  </object>
  <object>
    <name>person</name>
    <occluded>0</occluded>
    <bndbox>
      <xmin>1262.591796875</xmin>
      <ymin>44.25390625</ymin>
      <xmax>1289.2000000000007</xmax>
      <ymax>115.6883033752456</ymax>
    </bndbox>
  </object>
  <object>
    <name>person</name>
    <occluded>0</occluded>
    <bndbox>
      <xmin>1591.9501953125</xmin>
      <ymin>24.8447265625</ymin>
      <xmax>1629.5285453796387</xmax>
      <ymax>132.18915557861328</ymax>
    </bndbox>
  </object>
  <object>
    <name>person</name>
    <occluded>0</occluded>
    <bndbox>
      <xmin>1798.5</xmin>
      <ymin>591.2646484375</ymin>
      <xmax>1890.0187492370587</xmax>
      <ymax>773.9500000000025</ymax>
    </bndbox>
  </object>
  <object>
    <name>person</name>
    <occluded>0</occluded>
    <bndbox>
      <xmin>1380.0126953125</xmin>
      <ymin>0.0</ymin>
      <xmax>1420.865852355957</xmax>
      <ymax>63.482704162597656</ymax>
    </bndbox>
  </object>
  <object>
    <name>person</name>
    <occluded>0</occluded>
    <bndbox>
      <xmin>911.8994140625</xmin>
      <ymin>0.0</ymin>
      <xmax>949.7500000000018</xmax>
      <ymax>80.25281524658203</ymax>
    </bndbox>
  </object>
</annotation>
