<annotation>
  <folder></folder>
  <filename>315.jpg</filename>
  <source>
    <database>Unknown</database>
    <annotation>Unknown</annotation>
    <image>Unknown</image>
  </source>
  <size>
    <width>1920</width>
    <height>1080</height>
    <depth>3</depth>
  </size>
  <segmented>0</segmented>
  <object>
    <name>person</name>
    <occluded>0</occluded>
    <bndbox>
      <xmin>1040.48046875</xmin>
      <ymin>7.0068359375</ymin>
      <xmax>1090.7183593750015</xmax>
      <ymax>115.10781250000218</ymax>
    </bndbox>
  </object>
  <object>
    <name>person</name>
    <occluded>0</occluded>
    <bndbox>
      <xmin>1830.462890625</xmin>
      <ymin>595.41796875</ymin>
      <xmax>1920.0</xmax>
      <ymax>778.9009765625015</ymax>
    </bndbox>
  </object>
  <object>
    <name>person</name>
    <occluded>0</occluded>
    <bndbox>
      <xmin>1380.47216796875</xmin>
      <ymin>23.305957031251637</ymin>
      <xmax>1428.5933597564717</xmax>
      <ymax>155.9074241638191</ymax>
    </bndbox>
  </object>
  <object>
    <name>person</name>
    <occluded>0</occluded>
    <bndbox>
      <xmin>1259.959263392857</xmin>
      <ymin>984.9464285714286</ymin>
      <xmax>1360.3857142857148</xmax>
      <ymax>1080.0</ymax>
    </bndbox>
  </object>
  <object>
    <name>person</name>
    <occluded>0</occluded>
    <bndbox>
      <xmin>34.154296875</xmin>
      <ymin>127.3583984375</ymin>
      <xmax>95.17929687500146</xmax>
      <ymax>250.10000000000218</ymax>
    </bndbox>
  </object>
  <object>
    <name>person</name>
    <occluded>0</occluded>
    <bndbox>
      <xmin>333.548828125</xmin>
      <ymin>455.56103515625</ymin>
      <xmax>399.55117416381836</xmax>
      <ymax>608.9598632812522</ymax>
    </bndbox>
  </object>
  <object>
    <name>person</name>
    <occluded>0</occluded>
    <bndbox>
      <xmin>379.4302343750005</xmin>
      <ymin>477.0997265625007</ymin>
      <xmax>460.10273071288975</xmax>
      <ymax>635.8165142822251</ymax>
    </bndbox>
  </object>
  <object>
    <name>person</name>
    <occluded>0</occluded>
    <bndbox>
      <xmin>422.2746093750011</xmin>
      <ymin>469.6201171875</ymin>
      <xmax>469.666015625</xmax>
      <ymax>592.4427734375022</ymax>
    </bndbox>
  </object>
  <object>
    <name>person</name>
    <occluded>0</occluded>
    <bndbox>
      <xmin>449.49853515625</xmin>
      <ymin>482.14501953125</ymin>
      <xmax>502.1985351562507</xmax>
      <ymax>614.1446289062515</ymax>
    </bndbox>
  </object>
  <object>
    <name>person</name>
    <occluded>0</occluded>
    <bndbox>
      <xmin>1115.8984375</xmin>
      <ymin>4.100000000000364</ymin>
      <xmax>1139.9000000000015</xmax>
      <ymax>80.75000152587927</ymax>
    </bndbox>
  </object>
  <object>
    <name>person</name>
    <occluded>0</occluded>
    <bndbox>
      <xmin>1046.52734375</xmin>
      <ymin>93.189453125</ymin>
      <xmax>1085.6886756896965</xmax>
      <ymax>210.20000000000073</ymax>
    </bndbox>
  </object>
  <object>
    <name>person</name>
    <occluded>0</occluded>
    <bndbox>
      <xmin>733.048828125</xmin>
      <ymin>147.0830078125</ymin>
      <xmax>789.0666023254398</xmax>
      <ymax>296.61289062500146</ymax>
    </bndbox>
  </object>
  <object>
    <name>person</name>
    <occluded>0</occluded>
    <bndbox>
      <xmin>1267.4345703125</xmin>
      <ymin>54.8125</ymin>
      <xmax>1318.0000000000018</xmax>
      <ymax>187.64609375000146</ymax>
    </bndbox>
  </object>
  <object>
    <name>person</name>
    <occluded>0</occluded>
    <bndbox>
      <xmin>868.6502929687504</xmin>
      <ymin>12.57568359375</ymin>
      <xmax>912.1295940399159</xmax>
      <ymax>114.50839843750055</ymax>
    </bndbox>
  </object>
  <object>
    <name>person</name>
    <occluded>0</occluded>
    <bndbox>
      <xmin>928.357421875</xmin>
      <ymin>565.7685546875</ymin>
      <xmax>997.6000000000022</xmax>
      <ymax>745.6476562500011</ymax>
    </bndbox>
  </object>
  <object>
    <name>person</name>
    <occluded>0</occluded>
    <bndbox>
      <xmin>139.521484375</xmin>
      <ymin>221.3662109375</ymin>
      <xmax>214.39531250000073</xmax>
      <ymax>363.3500000000022</ymax>
    </bndbox>
  </object>
  <object>
    <name>person</name>
    <occluded>0</occluded>
    <bndbox>
      <xmin>752.9384765625</xmin>
      <ymin>462.578125</ymin>
      <xmax>823.0287109375022</xmax>
      <ymax>621.5500000000029</ymax>
    </bndbox>
  </object>
  <object>
    <name>person</name>
    <occluded>0</occluded>
    <bndbox>
      <xmin>931.75</xmin>
      <ymin>131.5078125</ymin>
      <xmax>997.2557849884015</xmax>
      <ymax>273.90000000000146</ymax>
    </bndbox>
  </object>
  <object>
    <name>person</name>
    <occluded>0</occluded>
    <bndbox>
      <xmin>0.0</xmin>
      <ymin>631.4246582031269</ymin>
      <xmax>118.69965953826932</xmax>
      <ymax>822.1706851959229</ymax>
    </bndbox>
  </object>
  <object>
    <name>person</name>
    <occluded>0</occluded>
    <bndbox>
      <xmin>1054.683984375</xmin>
      <ymin>672.7658203125</ymin>
      <xmax>1133.210000000002</xmax>
      <ymax>863.8100000000024</ymax>
    </bndbox>
  </object>
  <object>
    <name>person</name>
    <occluded>0</occluded>
    <bndbox>
      <xmin>1621.0000000000018</xmin>
      <ymin>50.3740234375</ymin>
      <xmax>1680.0970764160156</xmax>
      <ymax>176.8000000000011</ymax>
    </bndbox>
  </object>
  <object>
    <name>person</name>
    <occluded>0</occluded>
    <bndbox>
      <xmin>999.4765625</xmin>
      <ymin>140.689453125</ymin>
      <xmax>1043.6156257629373</xmax>
      <ymax>265.15625</ymax>
    </bndbox>
  </object>
  <object>
    <name>person</name>
    <occluded>0</occluded>
    <bndbox>
      <xmin>1539.7500000000018</xmin>
      <ymin>684.1923828125</ymin>
      <xmax>1622.5871047973633</xmax>
      <ymax>876.6000000000004</ymax>
    </bndbox>
  </object>
  <object>
    <name>person</name>
    <occluded>0</occluded>
    <bndbox>
      <xmin>1658.9000000000015</xmin>
      <ymin>47.5302734375</ymin>
      <xmax>1712.7814483642578</xmax>
      <ymax>169.8673828125011</ymax>
    </bndbox>
  </object>
  <object>
    <name>person</name>
    <occluded>0</occluded>
    <bndbox>
      <xmin>1433.4856770833333</xmin>
      <ymin>895.2024739583334</ymin>
      <xmax>1525.3513020833354</xmax>
      <ymax>1080.0</ymax>
    </bndbox>
  </object>
  <object>
    <name>person</name>
    <occluded>0</occluded>
    <bndbox>
      <xmin>1825.6492187500007</xmin>
      <ymin>65.482421875</ymin>
      <xmax>1892.848435211181</xmax>
      <ymax>193.70000000000255</ymax>
    </bndbox>
  </object>
  <object>
    <name>person</name>
    <occluded>0</occluded>
    <bndbox>
      <xmin>1794.7000000000025</xmin>
      <ymin>8.890625</ymin>
      <xmax>1852.1109447479248</xmax>
      <ymax>135.15000000000146</ymax>
    </bndbox>
  </object>
  <object>
    <name>person</name>
    <occluded>0</occluded>
    <bndbox>
      <xmin>1842.4500000000014</xmin>
      <ymin>128.94856770833334</ymin>
      <xmax>1912.254882176717</xmax>
      <ymax>263.2131703694661</ymax>
    </bndbox>
  </object>
  <object>
    <name>person</name>
    <occluded>0</occluded>
    <bndbox>
      <xmin>1721.7496093750015</xmin>
      <ymin>12.74609375</ymin>
      <xmax>1785.0970005035397</xmax>
      <ymax>133.90000000000146</ymax>
    </bndbox>
  </object>
  <object>
    <name>person</name>
    <occluded>0</occluded>
    <bndbox>
      <xmin>976.09765625</xmin>
      <ymin>40.4482421875</ymin>
      <xmax>1019.4744140625025</xmax>
      <ymax>154.0226562500011</ymax>
    </bndbox>
  </object>
  <object>
    <name>person</name>
    <occluded>0</occluded>
    <bndbox>
      <xmin>947.9001953125007</xmin>
      <ymin>0.0</ymin>
      <xmax>985.3001945495598</xmax>
      <ymax>108.85000000000218</ymax>
    </bndbox>
  </object>
</annotation>
