<annotation>
  <folder></folder>
  <filename>52.jpg</filename>
  <source>
    <database>Unknown</database>
    <annotation>Unknown</annotation>
    <image>Unknown</image>
  </source>
  <size>
    <width>1920</width>
    <height>1080</height>
    <depth>3</depth>
  </size>
  <segmented>0</segmented>
  <object>
    <name>person</name>
    <occluded>0</occluded>
    <bndbox>
      <xmin>1075.1100000000001</xmin>
      <ymin>674.496406250001</ymin>
      <xmax>1159.9799986267094</xmax>
      <ymax>869.5499957275395</ymax>
    </bndbox>
  </object>
  <object>
    <name>person</name>
    <occluded>0</occluded>
    <bndbox>
      <xmin>1192.879453125001</xmin>
      <ymin>736.8396484375</ymin>
      <xmax>1282.0451181030294</xmax>
      <ymax>908.7400000000019</ymax>
    </bndbox>
  </object>
  <object>
    <name>person</name>
    <occluded>0</occluded>
    <bndbox>
      <xmin>1556.7603515625</xmin>
      <ymin>668.1158593750002</ymin>
      <xmax>1648.9413671875034</xmax>
      <ymax>845.6100000000021</ymax>
    </bndbox>
  </object>
  <object>
    <name>person</name>
    <occluded>0</occluded>
    <bndbox>
      <xmin>1158.9067187500011</xmin>
      <ymin>364.64921875</ymin>
      <xmax>1218.1807806396487</xmax>
      <ymax>502.7400000000001</ymax>
    </bndbox>
  </object>
  <object>
    <name>person</name>
    <occluded>0</occluded>
    <bndbox>
      <xmin>681.9567187500004</xmin>
      <ymin>424.5921875</ymin>
      <xmax>747.2721875000018</xmax>
      <ymax>600.4200000000026</ymax>
    </bndbox>
  </object>
  <object>
    <name>person</name>
    <occluded>0</occluded>
    <bndbox>
      <xmin>121.698828125</xmin>
      <ymin>876.274609375</ymin>
      <xmax>244.80000000000072</xmax>
      <ymax>1054.7400000000023</ymax>
    </bndbox>
  </object>
  <object>
    <name>person</name>
    <occluded>0</occluded>
    <bndbox>
      <xmin>752.051171875</xmin>
      <ymin>297.140625</ymin>
      <xmax>807.1008587646472</xmax>
      <ymax>447.1999963378912</ymax>
    </bndbox>
  </object>
  <object>
    <name>person</name>
    <occluded>0</occluded>
    <bndbox>
      <xmin>1539.740234375</xmin>
      <ymin>512.4602343750015</ymin>
      <xmax>1618.000000000003</xmax>
      <ymax>686.5305404663086</ymax>
    </bndbox>
  </object>
  <object>
    <name>person</name>
    <occluded>0</occluded>
    <bndbox>
      <xmin>1844.4015625</xmin>
      <ymin>240.17835937500058</ymin>
      <xmax>1906.9599999999998</xmax>
      <ymax>378.06038940429863</ymax>
    </bndbox>
  </object>
  <object>
    <name>person</name>
    <occluded>0</occluded>
    <bndbox>
      <xmin>1753.439453125</xmin>
      <ymin>247.734375</ymin>
      <xmax>1820.236989746095</xmax>
      <ymax>399.9400000000023</ymax>
    </bndbox>
  </object>
  <object>
    <name>person</name>
    <occluded>0</occluded>
    <bndbox>
      <xmin>1743.720468750001</xmin>
      <ymin>162.128125</ymin>
      <xmax>1809.108520812988</xmax>
      <ymax>295.25895080566477</ymax>
    </bndbox>
  </object>
  <object>
    <name>person</name>
    <occluded>0</occluded>
    <bndbox>
      <xmin>1694.237890625</xmin>
      <ymin>66.68000000000248</ymin>
      <xmax>1749.3600000000013</xmax>
      <ymax>197.75999755859374</ymax>
    </bndbox>
  </object>
  <object>
    <name>person</name>
    <occluded>0</occluded>
    <bndbox>
      <xmin>1647.4798437500008</xmin>
      <ymin>35.1921875</ymin>
      <xmax>1692.2777099609375</xmax>
      <ymax>147.1605859375013</ymax>
    </bndbox>
  </object>
  <object>
    <name>person</name>
    <occluded>0</occluded>
    <bndbox>
      <xmin>1382.76875</xmin>
      <ymin>41.951953125</ymin>
      <xmax>1420.1257400512666</xmax>
      <ymax>175.98000000000172</ymax>
    </bndbox>
  </object>
  <object>
    <name>person</name>
    <occluded>0</occluded>
    <bndbox>
      <xmin>1191.2104687500018</xmin>
      <ymin>42.089453125</ymin>
      <xmax>1233.9200009155277</xmax>
      <ymax>172.45906494140507</ymax>
    </bndbox>
  </object>
  <object>
    <name>person</name>
    <occluded>0</occluded>
    <bndbox>
      <xmin>1153.740625</xmin>
      <ymin>61.196875</ymin>
      <xmax>1200.9206253051757</xmax>
      <ymax>181.84000000000088</ymax>
    </bndbox>
  </object>
  <object>
    <name>person</name>
    <occluded>0</occluded>
    <bndbox>
      <xmin>923.2732812500013</xmin>
      <ymin>266.40546875</ymin>
      <xmax>983.8195349121088</xmax>
      <ymax>410.0200000000019</ymax>
    </bndbox>
  </object>
  <object>
    <name>person</name>
    <occluded>0</occluded>
    <bndbox>
      <xmin>1102.8795312500006</xmin>
      <ymin>116.738671875</ymin>
      <xmax>1148.4200000000005</xmax>
      <ymax>229.5200000000019</ymax>
    </bndbox>
  </object>
  <object>
    <name>person</name>
    <occluded>0</occluded>
    <bndbox>
      <xmin>704.295703125</xmin>
      <ymin>119.31328125</ymin>
      <xmax>754.7800000000003</xmax>
      <ymax>254.860000000002</ymax>
    </bndbox>
  </object>
  <object>
    <name>person</name>
    <occluded>0</occluded>
    <bndbox>
      <xmin>578.0203125</xmin>
      <ymin>367.60703125</ymin>
      <xmax>649.3800000000003</xmax>
      <ymax>517.4599999999998</ymax>
    </bndbox>
  </object>
  <object>
    <name>person</name>
    <occluded>0</occluded>
    <bndbox>
      <xmin>577.208984375</xmin>
      <ymin>281.86000000000206</ymin>
      <xmax>629.919765930176</xmax>
      <ymax>386.0796890258789</ymax>
    </bndbox>
  </object>
  <object>
    <name>person</name>
    <occluded>0</occluded>
    <bndbox>
      <xmin>797.9012500000005</xmin>
      <ymin>52.77757812500058</ymin>
      <xmax>834.7006254577602</xmax>
      <ymax>178.57531127929687</ymax>
    </bndbox>
  </object>
  <object>
    <name>person</name>
    <occluded>0</occluded>
    <bndbox>
      <xmin>855.1000000000029</xmin>
      <ymin>60.207421875</ymin>
      <xmax>898.2538307189941</xmax>
      <ymax>185.74131469726564</ymax>
    </bndbox>
  </object>
  <object>
    <name>person</name>
    <occluded>0</occluded>
    <bndbox>
      <xmin>1000.4796875</xmin>
      <ymin>183.4</ymin>
      <xmax>1053.4396093749995</xmax>
      <ymax>327.76000549316524</ymax>
    </bndbox>
  </object>
  <object>
    <name>person</name>
    <occluded>0</occluded>
    <bndbox>
      <xmin>947.4390625</xmin>
      <ymin>19.473828125</ymin>
      <xmax>979.6068753051753</xmax>
      <ymax>137.06000000000057</ymax>
    </bndbox>
  </object>
  <object>
    <name>person</name>
    <occluded>0</occluded>
    <bndbox>
      <xmin>89.77390625000116</xmin>
      <ymin>121.050390625</ymin>
      <xmax>136.52525939941407</xmax>
      <ymax>240.71157196045095</ymax>
    </bndbox>
  </object>
  <object>
    <name>person</name>
    <occluded>0</occluded>
    <bndbox>
      <xmin>199.988671875</xmin>
      <ymin>625.1359375</ymin>
      <xmax>285.35960937500056</xmax>
      <ymax>811.8009356689442</ymax>
    </bndbox>
  </object>
  <object>
    <name>person</name>
    <occluded>0</occluded>
    <bndbox>
      <xmin>337.783203125</xmin>
      <ymin>483.6375</ymin>
      <xmax>401.22000000000116</xmax>
      <ymax>634.6828906249982</ymax>
    </bndbox>
  </object>
  <object>
    <name>person</name>
    <occluded>0</occluded>
    <bndbox>
      <xmin>384.196875</xmin>
      <ymin>502.55078125</ymin>
      <xmax>460.48000000000394</xmax>
      <ymax>661.3059619140629</ymax>
    </bndbox>
  </object>
  <object>
    <name>person</name>
    <occluded>0</occluded>
    <bndbox>
      <xmin>416.8400000000023</xmin>
      <ymin>478.93203125</ymin>
      <xmax>459.503670501709</xmax>
      <ymax>599.031640625</ymax>
    </bndbox>
  </object>
  <object>
    <name>person</name>
    <occluded>0</occluded>
    <bndbox>
      <xmin>454.0703125</xmin>
      <ymin>503.45078125</ymin>
      <xmax>505.78820312500176</xmax>
      <ymax>635.7566015625009</ymax>
    </bndbox>
  </object>
  <object>
    <name>person</name>
    <occluded>0</occluded>
    <bndbox>
      <xmin>1286.508203125</xmin>
      <ymin>0.0</ymin>
      <xmax>1325.3600000000013</xmax>
      <ymax>98.78000000000029</ymax>
    </bndbox>
  </object>
  <object>
    <name>person</name>
    <occluded>0</occluded>
    <bndbox>
      <xmin>1263.3800000000024</xmin>
      <ymin>36.572265625</ymin>
      <xmax>1287.9651927947998</xmax>
      <ymax>114.23617187500277</ymax>
    </bndbox>
  </object>
  <object>
    <name>person</name>
    <occluded>0</occluded>
    <bndbox>
      <xmin>1618.1395312500013</xmin>
      <ymin>41.654062500000876</ymin>
      <xmax>1659.9213097381567</xmax>
      <ymax>151.80008056640654</ymax>
    </bndbox>
  </object>
  <object>
    <name>person</name>
    <occluded>0</occluded>
    <bndbox>
      <xmin>1051.141796875</xmin>
      <ymin>949.3396484375</ymin>
      <xmax>1124.227065582277</xmax>
      <ymax>1080.0</ymax>
    </bndbox>
  </object>
  <object>
    <name>person</name>
    <occluded>0</occluded>
    <bndbox>
      <xmin>1732.5600000000006</xmin>
      <ymin>496.461328125</ymin>
      <xmax>1818.9189865112305</xmax>
      <ymax>668.4800000000025</ymax>
    </bndbox>
  </object>
  <object>
    <name>person</name>
    <occluded>0</occluded>
    <bndbox>
      <xmin>20.99921875</xmin>
      <ymin>72.84000000000233</ymin>
      <xmax>86.47921752929615</xmax>
      <ymax>175.819998779297</ymax>
    </bndbox>
  </object>
  <object>
    <name>person</name>
    <occluded>0</occluded>
    <bndbox>
      <xmin>1348.302734375</xmin>
      <ymin>0.0</ymin>
      <xmax>1390.8800000000017</xmax>
      <ymax>110.08000000000175</ymax>
    </bndbox>
  </object>
  <object>
    <name>person</name>
    <occluded>0</occluded>
    <bndbox>
      <xmin>904.5</xmin>
      <ymin>15.200000000002182</ymin>
      <xmax>942.660000000002</xmax>
      <ymax>137.13999786376954</ymax>
    </bndbox>
  </object>
</annotation>
